{"__type__":"cc.SpriteAtlas","_spriteFrames":{"label_bg":{"__uuid__":"f28DMycUhDSL4tRiuGaNMg"},"els_daily_login_bg":{"__uuid__":"a7ljaMftxFeLfBpOq8tsef"},"help":{"__uuid__":"6d2cfiYXdNopnD6QL3+HVb"},"select_gift_bg":{"__uuid__":"87kL9FAolMFIECIWNd0NVR"},"pause_bg":{"__uuid__":"73jC/VcE1JnqB1X8T9UKWJ"},"game_mask":{"__uuid__":"daTguw6v9ByIuLy6kh7qHC"},"els_daily_login_item_mask":{"__uuid__":"73c/6s22RPf6Hg0x/F7cBM"},"els_daily_login_item_bg":{"__uuid__":"d9pyAbmXdAe7GnpoUBlr11"},"select_gift_item_bg02":{"__uuid__":"1bDoHc0F1IEIqi98mr/fdI"},"pause_volume_close":{"__uuid__":"abgKzTll5C95EjfGHdSSon"},"pause_volume_bg":{"__uuid__":"b34lcYJcZGcIWqWtlx5sUp"},"pause_help_bg":{"__uuid__":"e4UsVC2lZLlr4kgtrciIe6"},"els_daily_login_icon_getted":{"__uuid__":"025QdsuWtKzY4NHUhOShk1"},"icon_circle_green":{"__uuid__":"709cSacrtBP6V/rHFoIa2y"},"pause_btn_bg1":{"__uuid__":"3ex+i9vMNEu56zFCCq7y55"},"select_gift_item_bg":{"__uuid__":"7btvWqqL1MkJry8iGdqqFw"},"light":{"__uuid__":"9aRs474mRNOp/IJeFxltYK"}}}